ye_tracker-0.0.3.dist-info/licenses/LICENSE
yetracker/__init__.py
yetracker/column.py
yetracker/common.py
yetracker/entry.py
yetracker/era.py
yetracker/raw_values.py
yetracker/tab.py
yetracker/tracker.py
yetracker/legacy/entries.py
yetracker/legacy/old_sheets.py
ye_tracker-0.0.3.dist-info/METADATA
ye_tracker-0.0.3.dist-info/WHEEL
ye_tracker-0.0.3.dist-info/top_level.txt
ye_tracker-0.0.3.dist-info/RECORD
