Metadata-Version: 2.4
Name: ye-tracker
Version: 0.0.3
Summary: A Python interface for the Ye Tracker.
Author-email: Phan Nguyên Khôi <fannk987@gmail.com>
Project-URL: Homepage, https://github.com/Robert-Phan/YeTrackerAPI/
Classifier: License :: OSI Approved :: MIT License
Requires-Python: >=3.12
License-File: LICENSE
Requires-Dist: google-api-python-client>=2.147.0
Dynamic: license-file
